singlearity/__init__.py
singlearity/api_client.py
singlearity/configuration.py
singlearity/exceptions.py
singlearity/rest.py
singlearity/api/__init__.py
singlearity/api/ap_is_api.py
singlearity/api/default_api.py
singlearity/models/__init__.py
singlearity/models/atmosphere.py
singlearity/models/body_get_game_sim_game_sim_post.py
singlearity/models/body_list_items_items_post.py
singlearity/models/game.py
singlearity/models/game_sim_results.py
singlearity/models/http_validation_error.py
singlearity/models/item.py
singlearity/models/lineup.py
singlearity/models/lineup_pos.py
singlearity/models/matchup.py
singlearity/models/player.py
singlearity/models/state.py
singlearity/models/team.py
singlearity/models/validation_error.py
singlearity/models/venue.py
singlearity-0.1.7.dist-info/METADATA
singlearity-0.1.7.dist-info/WHEEL
singlearity-0.1.7.dist-info/top_level.txt
singlearity-0.1.7.dist-info/RECORD
